README.rst
setup.py
wishbone_output_file/__init__.py
wishbone_output_file/fileout.py
wishbone_output_file.egg-info/PKG-INFO
wishbone_output_file.egg-info/SOURCES.txt
wishbone_output_file.egg-info/dependency_links.txt
wishbone_output_file.egg-info/entry_points.txt
wishbone_output_file.egg-info/namespace_packages.txt
wishbone_output_file.egg-info/not-zip-safe
wishbone_output_file.egg-info/requires.txt
wishbone_output_file.egg-info/top_level.txt