Metadata-Version: 1.1
Name: wishbone-output-file
Version: 3.0.0
Summary: A Wishbone output module to write event data to a file.
Home-page: https://github.com/smetj/wishbone-output-file
Author: Jelle Smet
Author-email: development@smetj.net
License: UNKNOWN
Download-URL: https://github.com/smetj/wishbone-xxx/tarball/master
Platform: Linux
Classifier: Development Status :: 5 - Production/Stable
Classifier: License :: OSI Approved :: GNU General Public License v3 or later (GPLv3+)
Classifier: Programming Language :: Python
Classifier: Intended Audience :: Developers
Classifier: Intended Audience :: System Administrators
